auto_app_panel/__init__.py
auto_app_panel/__main__.py
auto_app_panel/detector.py
auto_app_panel/extractors.py
auto_app_panel/generator.py
auto_app_panel/py.typed
auto_app_panel/types.py
auto_app_panel-0.1.3.dist-info/WHEEL
auto_app_panel-0.1.3.dist-info/entry_points.txt
auto_app_panel-0.1.3.dist-info/METADATA
auto_app_panel-0.1.3.dist-info/RECORD
