Metadata-Version: 2.3
Name: auto-app-panel
Version: 0.1.3
Summary: Automatically generate a Code Ocean App Panel from an argument parser defined in code.
Author: Ben Hardcastle
Author-email: Ben Hardcastle <ben.hardcastle@alleninstitute.org>
License: MIT
Classifier: Development Status :: 3 - Alpha
Classifier: Programming Language :: Python :: 3
Classifier: Programming Language :: Python :: 3.9
Classifier: Programming Language :: Python :: 3.10
Classifier: Programming Language :: Python :: 3.11
Classifier: Programming Language :: Python :: 3.12
Classifier: Programming Language :: Python :: 3.13
Classifier: License :: OSI Approved :: MIT License
Classifier: Operating System :: Microsoft :: Windows
Classifier: Operating System :: POSIX :: Linux
Requires-Dist: typer>=0.9.0
Requires-Dist: pydantic>=2.0.0
Requires-Dist: pydantic-settings>=2.0.0
Requires-Dist: eval-type-backport ; python_full_version == '3.9.*'
Requires-Python: >=3.9
Project-URL: Issues, https://github.com/bjhardcastle/auto-app-panel/issues
Project-URL: Repository, https://github.com/bjhardcastle/auto-app-panel
